Workbook

Sheet Datos
C1: Fecha Nueva
A2: Cotización | C2: 45210
A4: Tipo de Cambio | B4: 45210 | C4: 365.5 | D4: BNA | E4: https://www.bna.com.ar/Personas
A5: IGB003 | B5: Enebro Patagónico (Primera) | C5: 8931.92 | D5: Quilmes
A6: IGB014 | B6: Enebro Albania | C6: =44.5*1.1 -> 48.95 | E6: GARNIL | F6: * 05-10
A7: ICB003 | B7: Coriandro | C7: 1150 | E7: MELAR | F7: * 09-10
A8: ICB004 | B8: Cardamomo | C8: 38796 | E8: MELAR | F8: * 09-10
A9: ICB006 | B9: Clavo de Olor | C9: 23693 | E9: MELAR | F9: * 09-10
A10: ICB011 | B10: Cedron | C10: 2436 | E10: MELAR | F10: * 25-07
A11: ICB015 | B11: Flor de Azhar | C11: 16404.03 | D11: Quilmes
A12: ICB016 | B12: Aceite esencial Limon (ml) | C12: 69.5
A13: ICB017 | B13: Aceite esencial Pomelo (ml) | C13: 81
A14: ICAL003 | B14: ALCOHOL | C14: 366
A15: PACK43 | B15: Precinto termocontraible | C15: 2.7
A16: ICPA001 | B16: Pallet | C16: 1680 | D16: *1 pallet = 245 cajas = 980 botellas
A17: ICES001 | B17: Esquinero | C17: 230 | D17: *4 por pallet
A18: ICST001 | B18: Stretch | C18: 2619.71 | D18: * 1 rollo c/4 pallets
A19: PACK26 | B19: Etiquetas (2 x caja) Cod Cajas | C19: 14.35 | D19: * 2 x caja - 4 Botellas (de 1 etiqueta salen 2)
B20: Total: Palet, esquinero y estrichado | C20: =+(C16/980)+((C17*4)/980)+((C18/4)/980)+(C19/4) -> 6.9088546
A21: IGB007 | B21: Tapon | C21: 0.395 | D21: * | E21: PEÑON-TAPI desde 10-2023
A22: IGB001 | B22: Etiqueta | C22: 28.03 | E22: Quilmes
A23: IGB004 | B23: Botella | C23: 147.52 | D23: aumento 03-2023 | E23: Quilmes
A24: IGB005 | B24: Caja | C24: 85.35 | D24: * 4 botellas por caja | E24: Quilmes
A25: IGB006 | B25: Separador | C25: 20.37 | D25: * 1 separador por caja | E25: Quilmes
A26: Inflación s/INDEC | C26: 0.13 | D26: * estimado a revisar
A27: Aumento Sueldos Mes anterior | C27: 1.25 | D27: * Aumentos Abril 2023 y Julio 2023 - Octubre 2023 estimado a revisar
A29: Servicios e Indirectos | C29: 135
A30: Fasonado | C30: 250

Sheet Insumos
B1: Gin Bosque
A3: Alcohol 96% en el Macerador: | B3: 540
A5: Pink | H5: GF002
A6: Roble | B6: MACERACIÓN: | C6: Sí | G6: Litros resultantes/batch | H6: 880 | I6: Gin terminado (42%)
G8: 44738
A9: Serrano | E9: INSUMO | F9: Cantidad (gr) | G9: Costo por KG | H9: Costo/batch | I9: Costo/litro | J9: Costo/Botella
D10: IGB003 | E10: Enebro Patagónico | F10: =19282.5/2 -> 9641.25 | G10: =+Datos!C5 -> 8931.92 | H10: =G10*F10/$H$6 -> 97857.811 | I10: =+H10/$H$6 -> 111.20206 | J10: =I10/2 -> 55.601029
D11: ICB018 | E11: Enebro Albania | F11: =19282.5/2 -> 9641.25 | G11: =+Datos!C6*Datos!$C$4 -> 17891.225 | H11: =G11*F11/$H$6 -> 196015.65 | I11: =+H11/$H$6 -> 222.74506 | J11: =I11/2 -> 111.37253
D12: ICB003 | E12: Coriandro | F12: 3857.5 | G12: =+Datos!C7 -> 1150 | H12: =G12*F12/$H$6 -> 5041.0511 | I12: =+H12/$H$6 -> 5.7284672 | J12: =I12/2 -> 2.8642336
D13: ICB004 | E13: Cardamomo | F13: 61.5 | G13: =+Datos!C8 -> 38796 | H13: =G13*F13/$H$6 -> 2711.3114 | I13: =+H13/$H$6 -> 3.0810356 | J13: =I13/2 -> 1.5405178
D14: ICB006 | E14: Clavo de Olor | F14: 41.25 | G14: =+Datos!C9 -> 23693 | H14: =G14*F14/$H$6 -> 1110.6094 | I14: =+H14/$H$6 -> 1.2620561 | J14: =I14/2 -> 0.63102805
D15: ICB011 | E15: Cedron | F15: 900 | G15: =+Datos!C10 -> 2436 | H15: =G15*F15/$H$6 -> 2491.3636 | I15: =+H15/$H$6 -> 2.831095 | J15: =I15/2 -> 1.4155475
D16: ICB015 | E16: Flor de Azhar | F16: 514.25 | G16: =+Datos!C11 -> 16404.03 | H16: =G16*F16/$H$6 -> 9586.105 | I16: =+H16/$H$6 -> 10.893301 | J16: =I16/2 -> 5.4466506
D17: ICB016 | E17: Aceite esencial Limon (ml) | F17: 52.06 | G17: =+Datos!C12*Datos!$C$4 -> 25402.25 | H17: =G17*F17/$H$6 -> 1502.774 | I17: =+H17/$H$6 -> 1.7076977 | J17: =I17/2 -> 0.85384887
D18: ICB017 | E18: Aceite esencial Pomelo (ml) | F18: 21.1 | G18: =+Datos!C13*Datos!$C$4 -> 29605.5 | H18: =G18*F18/$H$6 -> 709.85915 | I18: =+H18/$H$6 -> 0.80665812 | J18: =I18/2 -> 0.40332906
E19: Total botánicos | F19: =SUM(F10:F18) -> 24730.16 | H19: =SUM(H10:H18) -> 317026.54 | I19: =SUM(I10:I18) -> 360.25743 | J19: =SUM(J10:J18) -> 180.12871
D20: ICAL003 | E20: ALCOHOL | F20: 540000 | G20: =+Datos!C14 -> 366 | H20: =G20*F20/$H$6 -> 224590.91 | I20: =+H20/$H$6 -> 255.21694 | J20: =I20/2 -> 127.60847
C22: Observaciones:
A23: Obser | D23: - Se machacan Enebro 5013,45 gr. (El 26%). El resto se pone en el macerado sin machacar -Se machacan Coriandro 347,2 gr. (El 9%). El resto se pone en el macerado sin machacar

Sheet Costeo
A2: Cotización | B2: x Botella 500cm3 | C2: 45180 | D2: =+Datos!C2 -> 45210
A3: Insumos Líquido | C3: 291.20256 | D3: =D4+D5 -> 307.73718
B4: Alcohol | C4: 117.14876 | D4: =Insumos!J20 -> 127.60847
B5: Botánicos | C5: 174.0538 | D5: =+Insumos!J19 -> 180.12871
A6: Insumos Packaging | C6: 280.74972 | D6: =D7+D8+D9+D10+D11+D12 -> 355.96135
A7: PACK43 | B7: Precinto termocontraible | C7: 2.4 | D7: =+Datos!C15 -> 2.7
B8: Palet, esquinero y estrichado | C8: 6.7397219 | D8: =+Datos!C20 -> 6.9088546
A9: IGB007 | B9: Tapon | C9: 69.63 | D9: =+Datos!C21*Datos!C4 -> 144.3725
A10: IGB001 | B10: Etiqueta | C10: 28.03 | D10: =+Datos!C22 -> 28.03
A11: IGB004 | B11: Botella | C11: 147.52 | D11: =+Datos!C23 -> 147.52
A12: IGB005 / IGB006 | B12: Caja + Separador (proporcional) | C12: 26.43 | D12: =+(Datos!C24+Datos!C25)/4 -> 26.43
A13: Otros Costos - 20% s/ Insumos | B13: 0.2 | C13: 114.39046 | D13: =+(D3+D6)*$B$13 -> 132.73971
A14: Servicios | C14: 401.2 | D14: =D15+D16 -> 483.356
B15: Servicios e indirectos | C15: 151.2 | D15: =+C15+C15*Datos!C26 -> 170.856
B16: Fazonado | C16: 250 | D16: =+C16*Datos!C27 -> 312.5
B17: TOTAL | C17: 1087.5427 | D17: =+D3+D6+D13+D14 -> 1279.7942
C20: Precio x Caja x 4 | D20: =+D17*4 -> 5119.177
A22: Consideraciones del presupuesto:
A23: Valores antes de impuestos (IVA e Internos).
A24: Costo por botella de 500cm3 en caja x 4 u. en palet de 245 cajas en 7 pisos.
A25: Incluye el costo del servicio, destilado, alcohol BCA 6 destilaciones, agua, Botánicos, Botella, etiquetas, tapón, caja, presinto de seguridad termocontraíble, palet, esquineros, estrichado
A26: NO incluye: cualquier otro elemento no mencionado
A27: Entrega en origen (Av Italia 900, Malagueño, Córdoba).
A28: Condicíon de pago 30 días.
A29: Se deberá contemplar un margen de seguridad por rotura y/o desperdicio de los insumos provistos por CMQ (+- 5%)
A30: Plazo de entrega: 20 días hábiles desde desde recibos los insumos (suponiendo pedido de un equipo).
A33: Fórmula de ajuste de precios
A34: Insumos | B34: Según cotización del mes * Desde 05-2022 se acuerda aplicar 20% sobre costo de insumos
A35: Servicios e indirectos | B35: Según Indice de Inflación INDEC
A36: Fazonado | B36: Según paritarias personal JM | C36: Ajustes habitualmente Febrerio y Agosto
