Workbook

Sheet Datos
C1: Fecha Nueva
A2: Cotización | C2: 45481
A4: Tipo de Cambio | B4: =+C2 -> 45481 | C4: 936.5 | D4: BNA | E4: https://www.bna.com.ar/Personas
A5: IGB003 | B5: Enebro Patagónico (Primera) | C5: 14290.88 | D5: Quilmes | F5: 45481
A6: IGB014 | B6: Enebro Albania | C6: =53.5 -> 53.5 | E6: GARNIL | F6: * 05-01 | H6: =+C6*C4 -> 50102.75
A7: ICB003 | B7: Coriandro | C7: 1711.15 | E7: MELAR | F7: * 09-01
A8: ICB004 | B8: Cardamomo | C8: 38796 | E8: MELAR | F8: * 09-01
A9: ICB006 | B9: Clavo de Olor | C9: 35104.2 | E9: MELAR | F9: * 09-01
A10: ICB011 | B10: Cedron | C10: 6904.4 | E10: MELAR | F10: *05-03
A11: ICB015 | B11: Flor de Azhar | C11: 16404.02 | D11: Quilmes | F11: 45390
A12: ICB016 | B12: Aceite esencial Limon (ml) | C12: 80.5
A13: ICB017 | B13: Aceite esencial Pomelo (ml) | C13: 235
A14: ICAL003 | B14: ALCOHOL | C14: 760
A15: PACK43 | B15: Precinto termocontraible | C15: 2.7
A16: ICPA001 | B16: Pallet | C16: 4010 | D16: *1 pallet = 245 cajas = 980 botellas
A17: ICES001 | B17: Esquinero | C17: 495 | D17: *4 por pallet
A18: ICST001 | B18: Stretch | C18: 3918.37 | D18: * 1 rollo c/4 pallets
A19: PACK26 | B19: Etiquetas (2 x caja) Cod Cajas | C19: 22.87 | D19: * 2 x caja - 4 Botellas (de 1 etiqueta salen 2)
B20: Total: Palet, esquinero y estrichado | C20: =+(C16/980)+((C17*4)/980)+((C18/4)/980)+(C19/4) -> 12.829329
A21: IGB007 | B21: Tapon | C21: 0.395 | D21: * | E21: PEÑON-TAPI desde 10-2023
A22: IGB001 | B22: Etiqueta | C22: 0.20114
A23: IGB004 | B23: Botella | C23: 351.05 | E23: Quilmes | F23: 45418
A24: IGB005 | B24: Caja | C24: 499 | D24: * 4 botellas por caja | E24: PEÑON-MULTICAJAS SA desde 13-11-2023 | J24: 85.35
A25: IGB006 | B25: Separador | C25: 98.93 | D25: * 1 separador por caja | E25: PEÑON-MULTICAJAS SA desde 13-11-2023 | J25: 20.37
A26: Inflación s/INDEC | C26: 0.092 | D26: *Mayo-Junio
A27: Aumento Sueldos Mes anterior | C27: 1.16 | D27: *Mayo-Junio
A29: Servicios e Indirectos | C29: 135
A30: Fasonado | C30: 250
A32: * Febrero Dto 12% respecto a Enero - baja costos / resignación de margen fasonado

Sheet Insumos
B1: Gin Bosque
A3: Alcohol 96% en el Macerador: | B3: 540
A5: Pink | H5: GF002
A6: Roble | B6: MACERACIÓN: | C6: Sí | G6: Litros resultantes/batch | H6: 880 | I6: Gin terminado (42%)
G8: 44738
A9: Serrano | E9: INSUMO | F9: Cantidad (gr) | G9: Costo por KG | H9: Costo/batch | I9: Costo/litro | J9: Costo/Botella
D10: IGB003 | E10: Enebro Patagónico | F10: =19282.5/2 -> 9641.25 | G10: =+Datos!C5 -> 14290.88 | H10: =G10*F10/$H$6 -> 156570.39 | I10: =+H10/$H$6 -> 177.9209 | J10: =I10/2 -> 88.960451
D11: IGB014 | E11: Enebro Albania | F11: =19282.5/2 -> 9641.25 | G11: =+Datos!C6*Datos!$C$4 -> 50102.75 | H11: =G11*F11/$H$6 -> 548924.02 | I11: =+H11/$H$6 -> 623.7773 | J11: =I11/2 -> 311.88865
D12: ICB003 | E12: Coriandro | F12: 3857.5 | G12: =+Datos!C7 -> 1711.15 | H12: =G12*F12/$H$6 -> 7500.8649 | I12: =+H12/$H$6 -> 8.5237101 | J12: =I12/2 -> 4.2618551
D13: ICB004 | E13: Cardamomo | F13: 61.5 | G13: =+Datos!C8 -> 38796 | H13: =G13*F13/$H$6 -> 2711.3114 | I13: =+H13/$H$6 -> 3.0810356 | J13: =I13/2 -> 1.5405178
D14: ICB006 | E14: Clavo de Olor | F14: 41.25 | G14: =+Datos!C9 -> 35104.2 | H14: =G14*F14/$H$6 -> 1645.5094 | I14: =+H14/$H$6 -> 1.869897 | J14: =I14/2 -> 0.93494851
D15: ICB011 | E15: Cedron | F15: 900 | G15: =+Datos!C10 -> 6904.4 | H15: =G15*F15/$H$6 -> 7061.3182 | I15: =+H15/$H$6 -> 8.0242252 | J15: =I15/2 -> 4.0121126
D16: ICB015 | E16: Flor de Azhar | F16: 514.25 | G16: =+Datos!C11 -> 16404.02 | H16: =G16*F16/$H$6 -> 9586.0992 | I16: =+H16/$H$6 -> 10.893295 | J16: =I16/2 -> 5.4466473
D17: ICB016 | E17: Aceite esencial Limon (ml) | F17: 52.06 | G17: =+Datos!C12*Datos!$C$4 -> 75388.25 | H17: =G17*F17/$H$6 -> 4459.9003 | I17: =+H17/$H$6 -> 5.0680686 | J17: =I17/2 -> 2.5340343
D18: ICB017 | E18: Aceite esencial Pomelo (ml) | F18: 21.1 | G18: =+Datos!C13*Datos!$C$4 -> 220077.5 | H18: =G18*F18/$H$6 -> 5276.8582 | I18: =+H18/$H$6 -> 5.9964298 | J18: =I18/2 -> 2.9982149
E19: Total botánicos | F19: =SUM(F10:F18) -> 24730.16 | H19: =SUM(H10:H18) -> 743736.28 | I19: =SUM(I10:I18) -> 845.15486 | J19: =SUM(J10:J18) -> 422.57743
D20: ICAL003 | E20: ALCOHOL | F20: 540000 | G20: =+Datos!C14 -> 760 | H20: =G20*F20/$H$6 -> 466363.64 | I20: =+H20/$H$6 -> 529.95868 | J20: =I20/2 -> 264.97934
C22: Observaciones:
A23: Obser | D23: - Se machacan Enebro 5013,45 gr. (El 26%). El resto se pone en el macerado sin machacar -Se machacan Coriandro 347,2 gr. (El 9%). El resto se pone en el macerado sin machacar

Sheet Costeo
A2: Cotización | B2: x Botella 500cm3 | C2: 45420 | D2: =+Datos!C2 -> 45481
A3: Insumos Líquido | C3: 641.65642 | D3: =D4+D5 -> 687.55677
B4: Alcohol | C4: 264.97934 | D4: =Insumos!J20 -> 264.97934
B5: Botánicos | C5: 376.67709 | D5: =+Insumos!J19 -> 422.57743
A6: Insumos Packaging | C6: 1049.5883 | D6: =D7+D8+D9+D10+D11+D12 -> 1074.3469
A7: PACK43 | B7: Precinto termocontraible | C7: 2.7 | D7: =+Datos!C15 -> 2.7
B8: Palet, esquinero y estrichado | C8: 10.127901 | D8: =+Datos!C20 -> 12.829329
A9: IGB007 | B9: Tapon | C9: 355.3025 | D9: =+Datos!C21*Datos!C4 -> 369.9175
A10: IGB001 | B10: Etiqueta | C10: 180.92543 | D10: =+Datos!C22*Datos!$C$4 -> 188.36761
A11: IGB004 | B11: Botella | C11: 351.05 | D11: =+Datos!C23 -> 351.05
A12: IGB005 / IGB006 | B12: Caja + Separador (proporcional) | C12: 149.4825 | D12: =+(Datos!C24+Datos!C25)/4 -> 149.4825
A13: Otros Costos - 20% s/ Insumos | B13: 0.2 | C13: 338.24895 | D13: =+(D3+D6)*$B$13 -> 352.38074
A14: Servicios | C14: 653.86986 | D14: =D15+D16 -> 734.79776
B15: Servicios e indirectos | C15: 348.40111 | D15: =+C15+C15*Datos!C26 -> 380.45401
B16: Fazonado | C16: 305.46875 | D16: =+C16*Datos!C27 -> 354.34375
B17: TOTAL | C17: 2683.3636 | D17: =+D3+D6+D13+D14 -> 2849.0822
C20: Precio x Caja x 4 | D20: =+D17*4 -> 11396.329
A22: Consideraciones del presupuesto:
A23: Valores antes de impuestos (IVA e Internos).
A24: Costo por botella de 500cm3 en caja x 4 u. en palet de 245 cajas en 7 pisos.
A25: Incluye el costo del servicio, destilado, alcohol BCA 6 destilaciones, agua, Botánicos, Botella, etiquetas, tapón, caja, presinto de seguridad termocontraíble, palet, esquineros, estrichado
A26: NO incluye: cualquier otro elemento no mencionado
A27: Entrega en origen (Av Italia 900, Malagueño, Córdoba).
A28: Condicíon de pago 30 días.
A29: Se deberá contemplar un margen de seguridad por rotura y/o desperdicio de los insumos provistos por CMQ (+- 5%)
A30: Plazo de entrega: 20 días hábiles desde desde recibos los insumos (suponiendo pedido de un equipo).
A33: Fórmula de ajuste de precios
A34: Insumos | B34: Según cotización del mes * Desde 05-2022 se acuerda aplicar 20% sobre costo de insumos
A35: Servicios e indirectos | B35: Según Indice de Inflación INDEC
A36: Fazonado | B36: Según paritarias personal JM | C36: Ajustes habitualmente Febrerio y Agosto

Sheet Insumos CMQ
A2: # | B2: Descripción | C2: Cotiz CMQ | D2: Cotiz Peñon | E2: Proveedor | F2: Fecha Cotiz
A3: 1 | B3: ENVASE BOTELLA AGROPECUARIA AMBAR 500ML | C3: 351.05 | D3: =+C3 -> 351.05 | E3: CMQ | F3: 45390
A4: 2 | B4: Caja Gin Bosque 500CC x4 | C4: 86.5 | D4: 469 | E4: MULTICAJAS S.A | F4: 45356
A5: 3 | B5: SEPARADORES CAJA GIN BOSQUE X4 | C5: 81.43 | D5: 75 | E5: MULTICAJAS S.A | F5: 45356
A6: 4 | B6: FLOR DE AZHAR | C6: 16596.6 | D6: =+C6 -> 16596.6 | E6: CMQ | F6: 45390
A7: 5 | B7: ENEBRO PRIMERA | C7: 8931.92 | D7: =+C7 -> 8931.92 | E7: CMQ | F7: 45390
A8: 6 | B8: CAJA GIN ALTA MONTANA 500CC X4 | C8: 10400.67 | D8: 255 | E8: MULTICAJAS S.A | F8: 45274
A9: 7 | B9: ETIQUETAS GIN ALTA MONTAÑA | C9: 27.54 | D9: =0.2*883.5 -> 176.7 | E9: ARTES GRAFICAS | F9: 45390
A10: 8 | B10: ETIQUETA GIN BOSQUE 500CC NUEVO EAN | C10: 28.04 | D10: =0.2*883.5 -> 176.7 | E10: ARTES GRAFICAS | F10: 45390
A11: 9 | B11: ETIQUETA GIN ALTA MONTANA X500 B4 | C11: 22.25 | D11: =0.2*883.5 -> 176.7 | E11: ARTES GRAFICAS | F11: 45390
B14: * Verificar error en precio insumo #6
B15: * Proveedor recomendado por CMQ - MULTICAJAS SA - No es conveniente en precio, incumple fechas de entrega. Ver posibilidad de que se pueda volver a comprar directo a CMQ.
B16: * Proveedor etiquetas mayor precio.
