Workbook

Sheet Datos
C1: Fecha Anterior | D1: Fecha Nueva
A2: Cotización | C2: 44835 | D2: 44866
A4: Copiar Valores mes anterior columna D y pegar en C | C4: 134.70758
A5: para comparativa mes anterior | C5: 55.109589
C6: 79.597987
C7: 164.98446
C8: 0.95
C9: 5.1144643
C10: 50.7
C11: 20.6
C12: 66.37
C13: 21.25
C14: 59.938408
C15: 92.785775
C16: 43.119575
C17: 49.6662
A19: Tipo de Cambio | B19: 44872 | C19: 164.5
A20: IGB003 | B20: Enebro Patagónico | C20: 4860
A21: ICB018 | B21: Enebro Polaco | C21: 6300
A22: ICB003 | B22: Coriandro | C22: 322
A23: ICB004 | B23: Cardamomo | C23: 18200
A24: ICB006 | B24: Clavo de Olor | C24: 3404
A25: ICB011 | B25: Cedron | C25: 794.14
A26: ICB015 | B26: Flor de Azhar | C26: 8892.75
A27: ICB016 | B27: Aceite esencial Limon (ml) | C27: 69.5
A28: ICB017 | B28: Aceite esencial Pomelo (ml) | C28: 81
A29: ICAL003 | B29: ALCOHOL | C29: 149 | D29: *
A30: PACK43 | B30: Precinto termocontraible | C30: 0.95
A31: ICPA001 | B31: Pallet | C31: 1067 | D31: *1 pallet = 245 cajas = 980 botellas
A32: ICES001 | B32: Esquinero | C32: 115 | D32: *4 por pallet
A33: ICST001 | B33: Stretch | C33: 1958.06 | D33: * 1 rollo c/4 pallets
A34: PACK26 | B34: Etiquetas (2 x caja) Cod Cajas | C34: 12.55 | D34: * 2 x caja - 4 Botellas (de 1 etiqueta salen 2) | F34: 12.55
B35: Total: Palet, esquinero y estrichado | C35: =+(C31/980)+((C32*4)/980)+((C33/4)/980)+(C34/4) -> 5.1951684
A36: IGB007 | B36: Tapon | C36: 50.7
A37: IGB001 | B37: Etiqueta | C37: 20.6
A38: IGB004 | B38: Botella | C38: 66.37
A39: IGB005 | B39: Caja | C39: 58.14 | D39: * 4 botellas por caja | G39: =+C39+C40 -> 80.29
A40: IGB006 | B40: Separador | C40: 22.15 | D40: * 1 separador por caja | G40: =+G39/3.778 -> 21.251985
A41: Inflación s/INDEC | C41: 0.062 | D41: * Ej. Al 30/09 - tomar Agosto
A42: Aumento Sueldos Mes anterior | C42: 0.22 | D42: * Aumento Septiembre 22%

Sheet Costeo
A2: Cotización | B2: x Botella 500cm3 | C2: =+Datos!C2 -> 44835 | D2: =+Datos!D2 -> 44866
A3: Insumos Líquido | C3: 102.76258 | D3: =D4+D5 -> 134.74133 | E3: * Para Gin Tonic
B4: Alcohol | C4: 40.8 | D4: =Insumos!J20 -> 55.109589
B5: Botánicos | C5: 61.96258 | D5: =+Insumos!J19 -> 79.631739
A6: Insumos Packaging | C6: 149.11 | D6: =D7+D8+D9+D10+D11+D12 -> 165.06517
A7: PACK43 | B7: Precinto termocontraible | C7: 0.9 | D7: =+Datos!C30 -> 0.95
B8: Palet, esquinero y estrichado | C8: 1.88 | D8: =+Datos!C35 -> 5.1951684 | E8: * incluye 2 etiquetas por caja por cod viejo
A9: IGB007 | B9: Tapon | C9: 45.6 | D9: =+Datos!C36 -> 50.7
A10: IGB001 | B10: Etiqueta | C10: 13.12 | D10: =+Datos!C37 -> 20.6
A11: IGB004 | B11: Botella | C11: 66.36 | D11: =+Datos!C38 -> 66.37
A12: IGB005 / IGB006 | B12: Caja + Separador (proporcional) | C12: 21.25 | D12: =+C12 -> 21.25
A13: Otros Costos - 20% s/ Insumos | B13: 0.2 | C13: 50.374516 | D13: =+(D3+D6)*$B$13 -> 59.961299
A14: Servicios | C14: 89.964869 | D14: =D15+D16 -> 103.38995
B15: Servicios e indirectos | C15: 40.298669 | D15: =C15*(1+Datos!C41) -> 42.797186 | E15: *7,4% inflación indec (Julio)
B16: Fazonado | C16: 49.6662 | D16: =+C16*(1+Datos!C42) -> 60.592764 | E16: * aumento 18% sueldos Julio
B17: TOTAL | C17: =+C3+C6+C13+C14 -> 392.21197 | D17: =+D3+D6+D13+D14 -> 463.15775
C20: Precio x Caja x 4 | D20: =+D17*4 -> 1852.631 | E20: =+D20/4 -> 463.15775
A22: Consideraciones del presupuesto:
A23: Valores antes de impuestos (IVA e Internos).
A24: Costo por botella de 500cm3 en caja x 4 u. en palet de 245 cajas en 7 pisos.
A25: Incluye el costo del servicio, destilado, alcohol BCA 6 destilaciones, agua, Botánicos, Botella, etiquetas, tapón, caja, presinto de seguridad termocontraíble, palet, esquineros, estrichado
A26: NO incluye: cualquier otro elemento no mencionado
A27: Entrega en origen (Av Italia 900, Malagueño, Córdoba).
A28: Condicíon de pago 30 días.
A29: Se deberá contemplar un margen de seguridad por rotura y/o desperdicio de los insumos provistos por CMQ (+- 5%)
A30: Plazo de entrega: 20 días hábiles desde desde recibos los insumos (suponiendo pedido de un equipo).
A33: Fórmula de ajuste de precios
A34: Insumos | B34: Según cotización del mes * Desde 05-2022 se acuerda aplicar 20% sobre costo de insumos
A35: Servicios e indirectos | B35: Según Indice de Inflación INDEC
A36: Fazonado | B36: Según paritarias personal JM | C36: Ajustes habitualmente Febrerio y Agosto

Sheet Insumos
B1: Gin Bosque Alta Montaña
A3: Alcohol 96% en el Macerador: | B3: 540
A5: Pink
A6: Roble | B6: MACERACIÓN: | C6: Sí | G6: Litros resultantes/batch | H6: 730 | I6: Gin terminado (53%)
A9: Serrano | E9: INSUMO | F9: Cantidad (gr) | G9: Costo por KG | H9: Costo/batch | I9: Costo/litro | J9: Costo/Botella
D10: IGB003 | E10: Enebro Patagónico | F10: =19282.5/2 -> 9641.25 | G10: =+Datos!C20 -> 4860 | H10: =G10*F10/1000 -> 46856.475 | I10: =+H10/$H$6 -> 64.186952 | J10: =I10/2 -> 32.093476
D11: ICB018 | E11: Enebro Polaco | F11: =19282.5/2 -> 9641.25 | G11: =+Datos!C21 -> 6300 | H11: =G11*F11/1000 -> 60739.875 | I11: =+H11/$H$6 -> 83.205308 | J11: =I11/2 -> 41.602654
D12: ICB003 | E12: Coriandro | F12: 3857.5 | G12: =+Datos!C22 -> 322 | H12: =G12*F12/1000 -> 1242.115 | I12: =+H12/$H$6 -> 1.7015274 | J12: =I12/2 -> 0.8507637
D13: ICB004 | E13: Cardamomo | F13: 61.5 | G13: =+Datos!C23 -> 18200 | H13: =G13*F13/1000 -> 1119.3 | I13: =+H13/$H$6 -> 1.5332877 | J13: =I13/2 -> 0.76664384
D14: ICB006 | E14: Clavo de Olor | F14: 41.25 | G14: =+Datos!C24 -> 3404 | H14: =G14*F14/1000 -> 140.415 | I14: =+H14/$H$6 -> 0.19234932 | J14: =I14/2 -> 0.096174658
D15: ICB011 | E15: Cedron | F15: 900 | G15: =+Datos!C25 -> 794.14 | H15: =G15*F15/1000 -> 714.726 | I15: =+H15/$H$6 -> 0.97907671 | J15: =I15/2 -> 0.48953836
D16: ICB015 | E16: Flor de Azhar | F16: 514.25 | G16: =+Datos!C26 -> 8892.75 | H16: =G16*F16/1000 -> 4573.0967 | I16: =+H16/$H$6 -> 6.264516 | J16: =I16/2 -> 3.132258
D17: ICB016 | E17: Aceite esencial Limon (ml) | F17: 52.06 | G17: =+Datos!C27*Datos!$C$19 -> 11432.75 | H17: =G17*F17/1000 -> 595.18897 | I17: =+H17/$H$6 -> 0.81532735 | J17: =I17/2 -> 0.40766367
D18: ICB017 | E18: Aceite esencial Pomelo (ml) | F18: 21.1 | G18: =+Datos!C28*Datos!$C$19 -> 13324.5 | H18: =G18*F18/1000 -> 281.14695 | I18: =+H18/$H$6 -> 0.38513281 | J18: =I18/2 -> 0.1925664
E19: Total botánicos | F19: =SUM(F10:F18) -> 24730.16 | H19: =SUM(H10:H18) -> 116262.34 | I19: =SUM(I10:I18) -> 159.26348 | J19: =SUM(J10:J18) -> 79.631739
D20: ICAL003 | E20: ALCOHOL | F20: 540000 | G20: =+Datos!C29 -> 149 | H20: =G20*F20/1000 -> 80460 | I20: =+H20/$H$6 -> 110.21918 | J20: =I20/2 -> 55.109589
C22: Observaciones:
A23: Obser | D23: - Se machacan Enebro 5013,45 gr. (El 26%). El resto se pone en el macerado sin machacar -Se machacan Coriandro 347,2 gr. (El 9%). El resto se pone en el macerado sin machacar
