Workbook

Sheet DATOS
C1: Fecha Anterior
A2: Cotización | C2: 45143
A5: Tipo de Cambio | B5: 45152 | C5: 365.5
A6: IGB003 | B6: Enebro Patagónico | C6: 8931.92 | D6: Quilmes
A7: ICB021 | B7: Enebro Albania | C7: =44.5*1.06 -> 47.17 | E7: GARNIL | F7: * 25-07
A8: ICB003 | B8: Coriandro | C8: 685.21 | E8: MELAR | F8: * 25-07
A9: ICB004 | B9: Cardamomo | C9: 23628 | E9: MELAR | F9: * 25-07
A10: ICB006 | B10: Clavo de Olor | C10: 13740 | E10: MELAR | F10: * 25-07
A11: ICB011 | B11: Cedron | C11: 2436 | E11: MELAR | F11: * 25-07
A12: ICB015 | B12: Flor de Azhar | C12: 16596.59 | D12: Quilmes
A13: ICB016 | B13: Aceite esencial Limon (ml) | C13: 69.5
A14: ICB017 | B14: Aceite esencial Pomelo (ml) | C14: 81
A15: ICAL003 | B15: ALCOHOL | C15: 285
A16: PACK43 | B16: Precinto termocontraible | C16: 2.11
A17: ICPA001 | B17: Pallet | C17: 1550 | D17: *1 pallet = 245 cajas = 980 botellas
A18: ICES001 | B18: Esquinero | C18: 226 | D18: *4 por pallet
A19: ICST001 | B19: Stretch | C19: 2619.71 | D19: * 1 rollo c/4 pallets
A20: PACK26 | B20: Etiquetas (2 x caja) Cod Cajas | C20: 11 | D20: * 2 x caja - 4 Botellas (de 1 etiqueta salen 2)
B21: Total: Palet, esquinero y estrichado | C21: =+(C17/980)+((C18*4)/980)+((C19/4)/980)+(C20/4) -> 5.922375
A22: IGB007 | B22: Tapon | C22: 69.63 | D22: * | E22: PEÑON-TAPI
A23: IGB002 | B23: Etiqueta | C23: 25.4 | E23: PEÑON-ASG
A24: IGB004 | B24: Botella | C24: 147.52 | D24: aumento 03-2023
A25: IGB005 | B25: Caja | C25: 98.93 | D25: * 4 botellas por caja | E25: PEÑON-MULTICAJAS SA
A26: IGB006 | B26: Separador | C26: 20.37 | D26: * 1 separador por caja | E26: PEÑON-MULTICAJAS SA
A27: Inflación s/INDEC | C27: 0.07 | D27: *
A28: Aumento Sueldos Mes anterior | C28: 1 | D28: * Aumentos Abril 2023 y Julio 2023
A30: Servicios e Indirectos | C30: 135
A31: Fasonado | C31: 250

Sheet Insumos
B1: Gin Bosque Alta Montaña
A3: Alcohol 96% en el Macerador: | B3: 540
A5: Pink | H5: GF003
A6: Roble | B6: MACERACIÓN: | C6: Sí | G6: Litros resultantes/batch | H6: 730 | I6: Gin terminado (53%)
A9: Serrano | E9: INSUMO | F9: Cantidad (gr) | G9: Costo por KG | H9: Costo/batch | I9: Costo/litro | J9: Costo/Botella
D10: IGB003 | E10: Enebro Patagónico | F10: =19282.5/2 -> 9641.25 | G10: =+DATOS!C6 -> 8931.92 | H10: =G10*F10/$H$6 -> 117965.58 | I10: =+H10/$H$6 -> 161.59669 | J10: =I10/2 -> 80.798343
D11: ICB021 | E11: Enebro Albania | F11: =19282.5/2 -> 9641.25 | G11: =+DATOS!C7*DATOS!$C$5 -> 17240.635 | H11: =G11*F11/$H$6 -> 227700.37 | I11: =+H11/$H$6 -> 311.91832 | J11: =I11/2 -> 155.95916
D12: ICB003 | E12: Coriandro | F12: 3857.5 | G12: =+DATOS!C8 -> 685.21 | H12: =G12*F12/$H$6 -> 3620.8186 | I12: =+H12/$H$6 -> 4.9600255 | J12: =I12/2 -> 2.4800127
D13: ICB004 | E13: Cardamomo | F13: 61.5 | G13: =+DATOS!C9 -> 23628 | H13: =G13*F13/$H$6 -> 1990.5781 | I13: =+H13/$H$6 -> 2.7268193 | J13: =I13/2 -> 1.3634096
D14: ICB006 | E14: Clavo de Olor | F14: 41.25 | G14: =+DATOS!C10 -> 13740 | H14: =G14*F14/$H$6 -> 776.40411 | I14: =+H14/$H$6 -> 1.0635673 | J14: =I14/2 -> 0.53178364
D15: ICB011 | E15: Cedron | F15: 900 | G15: =+DATOS!C11 -> 2436 | H15: =G15*F15/$H$6 -> 3003.2877 | I15: =+H15/$H$6 -> 4.1140927 | J15: =I15/2 -> 2.0570464
D16: ICB015 | E16: Flor de Azhar | F16: 514.25 | G16: =+DATOS!C12 -> 16596.59 | H16: =G16*F16/$H$6 -> 11691.502 | I16: =+H16/$H$6 -> 16.015756 | J16: =I16/2 -> 8.007878
D17: ICB016 | E17: Aceite esencial Limon (ml) | F17: 52.06 | G17: =+DATOS!C13*DATOS!$C$5 -> 25402.25 | H17: =G17*F17/$H$6 -> 1811.5632 | I17: =+H17/$H$6 -> 2.4815934 | J17: =I17/2 -> 1.2407967
D18: ICB017 | E18: Aceite esencial Pomelo (ml) | F18: 21.1 | G18: =+DATOS!C14*DATOS!$C$5 -> 29605.5 | H18: =G18*F18/$H$6 -> 855.72062 | I18: =+H18/$H$6 -> 1.17222 | J18: =I18/2 -> 0.58611001
E19: Total botánicos | F19: =SUM(F10:F18) -> 24730.16 | H19: =SUM(H10:H18) -> 369415.83 | I19: =SUM(I10:I18) -> 506.04908 | J19: =SUM(J10:J18) -> 253.02454
D20: ICAL003 | E20: ALCOHOL | F20: 540000 | G20: =+DATOS!C15 -> 285 | H20: =G20*F20/$H$6 -> 210821.92 | I20: =+H20/$H$6 -> 288.79715 | J20: =I20/2 -> 144.39857
C22: Observaciones:
A23: Obser | D23: - Se machacan Enebro 5013,45 gr. (El 26%). El resto se pone en el macerado sin machacar -Se machacan Coriandro 347,2 gr. (El 9%). El resto se pone en el macerado sin machacar

Sheet Costeo
A2: Cotización | B2: x Botella 500cm3 | D2: =+DATOS!C2 -> 45143
A3: Insumos Líquido | D3: =D4+D5 -> 397.42311
B4: Alcohol | D4: =Insumos!J20 -> 144.39857
B5: Botánicos | D5: =+Insumos!J19 -> 253.02454
A6: Insumos Packaging | D6: =D7+D8+D9+D10+D11+D12 -> 280.40738
A7: PACK43 | B7: Precinto termocontraible | D7: =+DATOS!C16 -> 2.11
B8: Palet, esquinero y estrichado | D8: =+DATOS!C21 -> 5.922375
A9: IGB007 | B9: Tapon | D9: =+DATOS!C22 -> 69.63
A10: IGB001 | B10: Etiqueta | D10: =+DATOS!C23 -> 25.4
A11: IGB004 | B11: Botella | D11: =+DATOS!C24 -> 147.52
A12: IGB005 / IGB006 | B12: Caja + Separador (proporcional) | D12: =+(DATOS!C25+DATOS!C26)/4 -> 29.825
A13: Otros Costos - 20% s/ Insumos | B13: 0.2 | D13: =+(D3+D6)*$B$13 -> 135.5661
A14: Servicios | D14: =D15+D16 -> 385
B15: Servicios e indirectos | D15: 135 | E15: *% inflación indec
B16: Fazonado | D16: 250
B17: TOTAL | D17: =+D3+D6+D13+D14 -> 1198.3966
C20: Precio x Caja x 4 | D20: =+D17*4 -> 4793.5863
A22: Consideraciones del presupuesto:
A23: Valores antes de impuestos (IVA e Internos).
A24: Costo por botella de 500cm3 en caja x 4 u. en palet de 245 cajas en 7 pisos.
A25: Incluye el costo del servicio, destilado, alcohol BCA 6 destilaciones, agua, Botánicos, Botella, etiquetas, tapón, caja, presinto de seguridad termocontraíble, palet, esquineros, estrichado
A26: NO incluye: cualquier otro elemento no mencionado
A27: Entrega en origen (Av Italia 900, Malagueño, Córdoba).
A28: Condicíon de pago 30 días.
A29: Se deberá contemplar un margen de seguridad por rotura y/o desperdicio de los insumos provistos por CMQ (+- 5%)
A30: Plazo de entrega: 20 días hábiles desde desde recibos los insumos (suponiendo pedido de un equipo).
A33: Fórmula de ajuste de precios
A34: Insumos | B34: Según cotización del mes * Desde 05-2022 se acuerda aplicar 20% sobre costo de insumos
A35: Servicios e indirectos | B35: Según Indice de Inflación INDEC
A36: Fazonado | B36: Según paritarias personal JM | C36: Ajustes habitualmente Febrerio y Agosto
