Workbook

Sheet DATOS
C1: Fecha Actual
A2: Cotización | C2: 45330
A5: Tipo de Cambio | B5: =+C2 -> 45330 | C5: 849.5
A6: IGB003 | B6: Enebro Patagónico | C6: 8688.81 | D6: Quilmes
A7: IGB014 | B7: Enebro Albania | C7: =53.5 -> 53.5 | E7: GARNIL | F7: * 02-11
A8: ICB003 | B8: Coriandro | C8: 1711.15 | E8: MELAR | F8: * 09-10
A9: ICB004 | B9: Cardamomo | C9: 38796 | E9: MELAR | F9: * 09-10
A10: ICB006 | B10: Clavo de Olor | C10: 35104.2 | E10: MELAR | F10: * 24-10
A11: ICB011 | B11: Cedron | C11: 6904.4 | E11: MELAR | F11: * 10-10
A12: ICB015 | B12: Flor de Azhar | C12: 16596.59 | D12: Quilmes
A13: ICB016 | B13: Aceite esencial Limon (ml) | C13: 80.5
A14: ICB017 | B14: Aceite esencial Pomelo (ml) | C14: 235
A15: ICAL003 | B15: ALCOHOL | C15: 700
A16: PACK43 | B16: Precinto termocontraible | C16: 2.7
A17: ICPA001 | B17: Pallet | C17: 3010 | D17: *1 pallet = 245 cajas = 980 botellas
A18: ICES001 | B18: Esquinero | C18: 250 | D18: *4 por pallet
A19: ICST001 | B19: Stretch | C19: 3918.37 | D19: * 1 rollo c/4 pallets
A20: PACK26 | B20: Etiquetas (2 x caja) Cod Cajas | C20: 14.35 | D20: * 2 x caja - 4 Botellas (de 1 etiqueta salen 2)
B21: Total: Palet, esquinero y estrichado | C21: =+(C17/980)+((C18*4)/980)+((C19/4)/980)+(C20/4) -> 8.6789209
A22: IGB007 | B22: Tapon | C22: 0.395 | D22: * | E22: PEÑON-TAPI
A23: IGB002 | B23: Etiqueta | C23: 22.25 | E23: PEÑON-ASG
A24: IGB004 | B24: Botella | C24: 224.21 | D24: aumento 03-2023
A25: IGB005 | B25: Caja | C25: 255 | D25: * 4 botellas por caja | E25: PEÑON-MULTICAJAS SA desde 13-11-2023 | J25: 98.93
A26: IGB006 | B26: Separador | C26: 42.5 | D26: * 1 separador por caja | E26: PEÑON-MULTICAJAS SA desde 13-11-2023 | J26: 20.37
A27: Inflación s/INDEC | C27: 0 | D27: *
A28: Aumento Sueldos Mes anterior | C28: 1 | D28: * Aumentos Abril 2023 y Julio 2023 - Octubre 2023 estimado a revisar-Dic estimado revisar
A30: Servicios e Indirectos | C30: 135
A31: Fasonado | C31: 250
A34: * Febrero Dto 12% respecto a Enero - baja costos / resignación de margen fasonado

Sheet Insumos
B1: Gin Bosque Alta Montaña
A3: Alcohol 96% en el Macerador: | B3: 540
A5: Pink | H5: GF003
A6: Roble | B6: MACERACIÓN: | C6: Sí | G6: Litros resultantes/batch | H6: 730 | I6: Gin terminado (53%)
A9: Serrano | E9: INSUMO | F9: Cantidad (gr) | G9: Costo por KG | H9: Costo/batch | I9: Costo/litro | J9: Costo/Botella
D10: IGB003 | E10: Enebro Patagónico | F10: =19282.5/2 -> 9641.25 | G10: =+DATOS!C6 -> 8688.81 | H10: =G10*F10/$H$6 -> 114754.78 | I10: =+H10/$H$6 -> 157.19833 | J10: =I10/2 -> 78.599164
D11: ICB021 | E11: Enebro Albania | F11: =19282.5/2 -> 9641.25 | G11: =+DATOS!C7*DATOS!$C$5 -> 45448.25 | H11: =G11*F11/$H$6 -> 600243.75 | I11: =+H11/$H$6 -> 822.25172 | J11: =I11/2 -> 411.12586
D12: ICB003 | E12: Coriandro | F12: 3857.5 | G12: =+DATOS!C8 -> 1711.15 | H12: =G12*F12/$H$6 -> 9042.1385 | I12: =+H12/$H$6 -> 12.386491 | J12: =I12/2 -> 6.1932456
D13: ICB004 | E13: Cardamomo | F13: 61.5 | G13: =+DATOS!C9 -> 38796 | H13: =G13*F13/$H$6 -> 3268.4301 | I13: =+H13/$H$6 -> 4.4773016 | J13: =I13/2 -> 2.2386508
D14: ICB006 | E14: Clavo de Olor | F14: 41.25 | G14: =+DATOS!C10 -> 35104.2 | H14: =G14*F14/$H$6 -> 1983.6277 | I14: =+H14/$H$6 -> 2.7172983 | J14: =I14/2 -> 1.3586491
D15: ICB011 | E15: Cedron | F15: 900 | G15: =+DATOS!C11 -> 6904.4 | H15: =G15*F15/$H$6 -> 8512.274 | I15: =+H15/$H$6 -> 11.660649 | J15: =I15/2 -> 5.8303246
D16: ICB015 | E16: Flor de Azhar | F16: 514.25 | G16: =+DATOS!C12 -> 16596.59 | H16: =G16*F16/$H$6 -> 11691.502 | I16: =+H16/$H$6 -> 16.015756 | J16: =I16/2 -> 8.007878
D17: ICB016 | E17: Aceite esencial Limon (ml) | F17: 52.06 | G17: =+DATOS!C13*DATOS!$C$5 -> 68384.75 | H17: =G17*F17/$H$6 -> 4876.8631 | I17: =+H17/$H$6 -> 6.6806344 | J17: =I17/2 -> 3.3403172
D18: ICB017 | E18: Aceite esencial Pomelo (ml) | F18: 21.1 | G18: =+DATOS!C14*DATOS!$C$5 -> 199632.5 | H18: =G18*F18/$H$6 -> 5770.1997 | I18: =+H18/$H$6 -> 7.9043831 | J18: =I18/2 -> 3.9521915
E19: Total botánicos | F19: =SUM(F10:F18) -> 24730.16 | H19: =SUM(H10:H18) -> 760143.57 | I19: =SUM(I10:I18) -> 1041.2926 | J19: =SUM(J10:J18) -> 520.64628
D20: ICAL003 | E20: ALCOHOL | F20: 540000 | G20: =+DATOS!C15 -> 700 | H20: =G20*F20/$H$6 -> 517808.22 | I20: =+H20/$H$6 -> 709.32633 | J20: =I20/2 -> 354.66316
C22: Observaciones:
A23: Obser | D23: - Se machacan Enebro 5013,45 gr. (El 26%). El resto se pone en el macerado sin machacar -Se machacan Coriandro 347,2 gr. (El 9%). El resto se pone en el macerado sin machacar

Sheet Costeo
A2: Cotización | B2: x Botella 500cm3 | C2: 45300 | D2: =+DATOS!C2 -> 45330
A3: Insumos Líquido | C3: 955.33473 | D3: =D4+D5 -> 875.30944
B4: Alcohol | C4: 390.12948 | D4: =Insumos!J20 -> 354.66316
B5: Botánicos | C5: 565.20525 | D5: =+Insumos!J19 -> 520.64628
A6: Insumos Packaging | C6: 661.44642 | D6: =D7+D8+D9+D10+D11+D12 -> 667.76642
A7: PACK43 | B7: Precinto termocontraible | C7: 2.7 | D7: =+DATOS!C16 -> 2.7
B8: Palet, esquinero y estrichado | C8: 8.6789209 | D8: =+DATOS!C21 -> 8.6789209
A9: IGB007 | B9: Tapon | C9: 329.2325 | D9: =+DATOS!C22*DATOS!C5 -> 335.5525
A10: IGB001 | B10: Etiqueta | C10: 22.25 | D10: =+DATOS!C23 -> 22.25
A11: IGB004 | B11: Botella | C11: 224.21 | D11: =+DATOS!C24 -> 224.21
A12: IGB005 / IGB006 | B12: Caja + Separador (proporcional) | C12: 74.375 | D12: =+(DATOS!C25+DATOS!C26)/4 -> 74.375
A13: Otros Costos - 20% s/ Insumos | B13: 0.2 | C13: 323.35623 | D13: =+(D3+D6)*$B$13 -> 308.61517
A14: Servicios | C14: 797.98723 | D14: =D15+D16 -> 547.98723
B15: Servicios e indirectos | C15: 282.36223 | D15: =+C15+C15*DATOS!C27 -> 282.36223 | E15: *% inflación indec
B16: Fazonado | C16: 515.625 | D16: =+C16*DATOS!C28-250 -> 265.625
B17: TOTAL | C17: 2738.1246 | D17: =+D3+D6+D13+D14 -> 2399.6783
C20: Precio x Caja x 4 | D20: =+D17*4 -> 9598.7131
A22: Consideraciones del presupuesto:
A23: Valores antes de impuestos (IVA e Internos).
A24: Costo por botella de 500cm3 en caja x 4 u. en palet de 245 cajas en 7 pisos.
A25: Incluye el costo del servicio, destilado, alcohol BCA 6 destilaciones, agua, Botánicos, Botella, etiquetas, tapón, caja, presinto de seguridad termocontraíble, palet, esquineros, estrichado
A26: NO incluye: cualquier otro elemento no mencionado
A27: Entrega en origen (Av Italia 900, Malagueño, Córdoba).
A28: Condicíon de pago 30 días.
A29: Se deberá contemplar un margen de seguridad por rotura y/o desperdicio de los insumos provistos por CMQ (+- 5%)
A30: Plazo de entrega: 20 días hábiles desde desde recibos los insumos (suponiendo pedido de un equipo).
A33: Fórmula de ajuste de precios
A34: Insumos | B34: Según cotización del mes * Desde 05-2022 se acuerda aplicar 20% sobre costo de insumos
A35: Servicios e indirectos | B35: Según Indice de Inflación INDEC
A36: Fazonado | B36: Según paritarias personal JM | C36: Ajustes habitualmente Febrerio y Agosto
