Workbook

Sheet DATOS
A1: Concepto/Insumo | B1: Observaciones | E1: Costos 60.000 U
A2: Unidades OC | E2: 60000
A3: Total Litros | B3: 0.269 | E3: =+E2*B3 -> 16140 | G3: Litros a Producir | H3: =+E3*1.05 -> 16947
A4: Latas Por Bulto | E4: 24
A5: Bultos x 24 por Pallet | B5: 13 Pisos - 12 por piso | E5: 156
A6: Latas por Pallet | E6: =+E4*E5 -> 3744
A7: Pallets | E7: =+E2/E4/E5 -> 16.025641
A8: Dolar hoy | B8: BNA | C8: Pesos | D8: 44865 | E8: 161.5
A9: Lata + Tapa | B9: CMQ | C9: Pesos | E9: 12.77
A10: Funda termocontraible | B10: Raal | C10: USD | D10: 44865 | E10: =86/1000 -> 0.086 | F10: *14-09-22 Aumento de USD 72 a USD 86 el millar
A11: 6-pack Impreso | B11: Petropack/Envases Lavalle | C11: USD | E11: 6.9 | F11: 1,66 Grs por Kilo | G11: * Revisar - Presup pte | I11: =1.66/1000*E2 -> 99.6
A12: 4x6-pack (Termo) | B12: Petropack/Envases Lavalle | C12: USD | E12: 3.8 | F12: 0,89 Grs por Kilo | G12: * Revisar - Presup pte | I12: =0.89/1000*E2 -> 53.4
A13: Bandeja | B13: Quien provee? | C13: Pesos | E13: 0.04 | G13: * Revisar
A14: Líquido Gin Tonic Bosque por Lata | B14: JM | C14: Pesos | E14: =+'GIN TONIC'!E10 -> 50.440863
A15: Transporte Cisterna | B15: Silvia Casari? Talca 30-40 d | C15: Pesos | E15: 260000 | F15: precio independiente de cant litros - Máximo 35,000 Lts
A16: Streetch | C16: Pesos | E16: 0.54 | F16: estimado CMQ - Ok 14-09
A17: Pallet | C17: Pesos | E17: 2.06 | F17: estimado CMQ - Ok 14-09
A18: Interlayer | B18: Cartocor | C18: Pesos | E18: 7.14 | F18: Revisar Presupuesto
A19: * Costo Análisis del líquido

Sheet GIN TONIC
A1: Cotización por Litro de Gin Tonic
A2: Componente | B2: Cantidad a utilizar | C2: Unidad de uso | D2: Costo insumo unidad de uso en PESOS | E2: Costo estimado de producción x Litro en PESOS
A3: Gin Bosque x litro | B3: 0.2 | C3: Litros | D3: =(111.31*2)*1.2 -> 267.144 | E3: =+D3*B3 -> 53.4288 | F3: *costo insumos según cotización 10-2022 Bosque
A4: Tonica produccion propia | B4: 0.8 | C4: Litros | D4: =20*1.15 -> 23 | E4: =+D4*B4 -> 18.4
A5: Indirectos + mo | B5: 0.2 | C5: Litros | D5: =(46.14*2) -> 92.28 | E5: =D5*B5 -> 18.456
A6: Servicio de fazonado Gin | B6: 0.2 | C6: Litros | D6: =(60.59*2)*0.7 -> 84.826 | E6: =+B6*D6 -> 16.9652 | F6: * según cotización Bosque 10-2022
A7: Margen de seguridad | B7: 0.05 | E7: =+B7*(E3+E4+E5+E6) -> 5.3625
A8: Servicio de fazonado Gin Tonic | E8: =70*1.07 -> 74.9 | F8: *incluye: Mano de obra, Destilación, Producción de la tónica según receta propia de JM, Mezcla
E9: =SUM(E3:E8) -> 187.5125 | F9: TOTAL
D10: Fason x 269 | E10: =E9*0.269 -> 50.440863 | F10: actualizado a Octubre
A11: Fórmula de ajuste de precios
A12: Insumos | B12: Según cotización del mes * Desde 05-2022 se acuerda aplicar 20% sobre costo de insumos
A13: Servicios e indirectos | B13: Según Indice de Inflación INDEC
A14: Fazonado | B14: Según paritarias personal JM | C14: Ajustes habitualmente Febrerio y Agosto
D15: ,
A20: *

Sheet Bosque Nativo -Peñon
A1: USD CMQ BGT 2022 | B1: 125.22 | C1: * Actualizar CMQ
A2: Dolar hoy | B2: =+DATOS!E8 -> 161.5
A4: GT
A5: COPACKER: PEÑON DEL AGUILA | B5: proveedor | C5: Valor al 31/10 | D5: Plazo | E5: Observaciones
A6: Produccion (latas) | C6: 60000 | F6: =C6*0.269 -> 16140 | G6: litros en lata
A7: Producción (HL) | C7: =+C6*0.269/100 -> 161.4 | F7: =+F6*1.015 -> 16382.1 | G7: enviar + 1,5% desp | K7: 1 | L7: 1000
A8: COSTO POR LATA | C8: 4x6 269 | K8: =+L8/L7 -> 0.00166 | L8: 1.66
A9: Lata+Tapa | B9: CMQ | C9: =+DATOS!E9 -> 12.77 | D9: 45 | K9: =+K8*60000 -> 99.6
A10: Funda termocontraible | B10: Raal | C10: =+DATOS!E10*'Bosque Nativo -Peñon'!B2 -> 13.889 | D10: 60 | E10: ver si mejora por 120K (coti actual por 60k) | I10: 60000
A11: 6-pack Impreso | B11: Petropack | C11: =DATOS!E11*DATOS!E8*1.66/1000 -> 1.849821 | E11: VER ESTO CON BRUNO. Pedido mínimo? 500kg. Plazo de pago? | F11: 1,66 GRS POR KILO | H11: =1000/1.66 -> 602.40964 | I11: =+I10/H11 -> 99.6 | K11: =100*602 -> 60200 | L11: =+K11/6 -> 10033.333
A12: 4x6-pack (Termo) | B12: Petropack | C12: =DATOS!E12*DATOS!E8*0.89/1000 -> 0.546193 | E12: VER ESTO CON BRUNO. Pedido mínimo? 500kg. Plazo de pago? | F12: 0,89 GRS POR KILO | H12: =1000/0.89 -> 1123.5955 | I12: =+I10/H12 -> 53.4 | K12: =1123*54 -> 60642 | L12: =+K12/24 -> 2526.75
A13: Polimeros | B13: Petropack | C13: 6.35
A14: Bandeja | B14: Quien provee? | C14: =+DATOS!E13 -> 0.04 | E14: Corroborar costo, cantidad a usar, proveedor, plazo | F14: referencia CMQ
A15: Liquido | B15: JM | C15: =+DATOS!E14*1.015 -> 51.197475 | E15: *Desperdicio s/Talca 1,5% - Enviar 16.382 Litros
A16: Transporte Cisterna | B16: Silvia Casari? | C16: =+DATOS!E15/DATOS!E2 -> 4.3333333 | D16: 45 | E16: Costo por Cisterna - Cap Max 35.000 litros | H16: camión de 35.000
A17: Streetch | C17: =+DATOS!E16*DATOS!$B$3 -> 0.14526 | E17: Estimado CMQ - Ok según estimado Peñón
A18: Pallet | C18: =+DATOS!E17*DATOS!$B$3 -> 0.55414 | E18: Estimado CMQ - Ok según estimado Peñón
A19: Interlayer | B19: Cartocor | C19: =+DATOS!E18*DATOS!$B$3 -> 1.92066 | E19: Solicitar Presupuesto, cantidad a usar 13 por pallet, proveedor Cartocor, plazo
A20: COSTO INSUMOS | C20: =+SUM(C9:C19) -> 93.595883 | L20: =13*12 -> 156
A21: Costo Fraccionamiento/Envasado | B21: Talca | C21: 23.55 | D21: =565.09/24 -> 23.545417 | E21: Plazo de pago- 30+10 | L21: =+L20*24 -> 3744 | M21: latas x pallet | O21: =120000/L21 -> 32.051282 | P21: =O21*13 -> 416.66667
A22: Gestion insumos (20%) | B22: JM | C22: =0.2*(C21+C20) -> 23.429177 | D22: =+D21/C21 -> 0.99980538
A23: COSTO PRODUCTO SIN IMPUESTOS | C23: =+SUM(C20:C22) -> 140.57506 | L23: =+L21*#REF! -> #REF! | M23: VIC 1 pallet
A24: Impuestos Internos 8,7% | C24: =+C23*8.69% -> 12.215973
A25: Costo Logistico de Insumos (Latas MDZ) | C25: 0 | D25: 0 | E25: No entra en nuestro costeo/factura
A26: TOTAL x Lata ($) | C26: =+SUM(C23:C24)+C25 -> 152.79103
E27: Cuánto líquido necesitan? por el desperdicio en talca - 1,5% desperdicio
A28: VIC x Lata en USD | C28: =+(C26/$B$1) -> 1.2201807
A29: Volumen Referencia (latas) | C29: =+C6 -> 60000
A30: VIC/HL en USD | C30: =+C28/0.269*100 -> 453.59879
A32: * Valores Actualizados al 31-10-2022. Sujetos a revisión al momento de la producción definitiva. Ajustar OC según precio confirmado.
A39: COSTO POR LITRO
A40: Liquido
A41: Packaging
A42: Indirectos
A43: COSTO INSUMOS
A44: Costo Producción + Rentabilidad + Financieros
A45: COSTO PRODUCTO SIN IMPUESTOS
A46: Impuestos Internos 35,14%
A47: TOTAL x Litro ($)

Sheet Planificación Insumos
B1: Proveedor | C1: Fecha | D1: Plazo | E1: Fecha Cobro
A2: Fecha Producción Gin Tonic
A3: Fecha Entrega Líquido a Talca | C3: 44859
A4: Fecha Finalización Talca | C4: 44860 | D4: 40 | E4: =+C4+D4 -> 44900
A6: Insumos | B6: Proveedor | C6: Fecha | D6: Plazo Pago | E6: Fecha Pago
A7: Lata + Tapa | B7: Quilmes | C7: 44855 | D7: 30 | E7: =+C7+D7 -> 44885 | G7: Envía Quilmes a Talca directamente - Factura a JMK -Las latas deben llegar 3 días antes del fraccionamiento, no antes, porque no hay espacio para almacenar.
A8: Funda Termocontraible | B8: Artes Graficas | C8: 44849 | D8: 60 | E8: =+C8+D8 -> 44909 | G8: Ver aprobación de Artes - luego 40 dias para produccion
A9: 6-pack Impreso | B9: Envases Lavalle | D9: 30 | G9: a medida que esté listo el packagin se lo puedan enviar una semana antes. No hay problema.
A10: 4x6-pack (Termo) | B10: Envases Lavalle | D10: 30 | G10: plazo pago contra entrega según fecha factura
A11: Bandeja | B11: Ver proveedor
A12: Líquido Gin Tonic Bosque por Lata | G12: el líquido hay que coordinar con camión cisterna para que le llegue 1 día antes
A13: Transporte Cisterna | D13: 30 | F13: Silvia | G13: El camión cisterna debe llegar con Remito y Análisis de la bebida, donde se indique alcohol, NTU, PH, Acidez, Brix y cualquier otro parámetro que ustedes midan. Debe llegar precintado en válvulas y tapas, con la numeración colocada en el remito o protocolo aparte. (Si, con el de ustedes es suficiente. Cuando llega el camión lo muestreamos y se compara contra ese análisis que nos envían. Si todo esta OK, descargamos el líquido y fraccionamos.)
A14: Streetch | B14: Proveedor Habitual | D14: 30 | G14: ** Ver cantidad para enviar a Talca??
A15: Pallet | B15: Proveedor Habitual | D15: 30 | G15: ** Ver cantidad para enviar a Talca??
A16: Interlayer | B16: Cartocor ? | D16: 0
A17: Fraccionamiento Talca | C17: 44860 | D17: 40 | E17: =+C17+D17 -> 44900 | F17: Lucas Millan | G17: reservado turno para enlatar 60.000 unidades de lata 269ml en la última semana de octubre. Es factible hacerlo en esa semana, de todos modos hay que ir vendo como llegamos a la fecha. Lo que no puede pasar es que me avisen sobre la fecha que no lleguen porque la programación es mes a mes y pierdo el día de producción.

Sheet analisis
